llamux/__init__.py
llamux/main.py
llamux-0.1.9.dist-info/LICENSE
llamux-0.1.9.dist-info/METADATA
llamux-0.1.9.dist-info/WHEEL
llamux-0.1.9.dist-info/RECORD
