Metadata-Version: 2.1
Name: llamux
Version: 0.1.9
Summary: A simple llm router
License: MIT
Author: Andrea Pinto
Author-email: ap@agpinto.com
Requires-Python: >=3.11,<4.0
Classifier: License :: OSI Approved :: MIT License
Classifier: Programming Language :: Python :: 3
Classifier: Programming Language :: Python :: 3.11
Classifier: Programming Language :: Python :: 3.12
Classifier: Programming Language :: Python :: 3.13
Requires-Dist: litellm (>=1.54.1,<2.0.0)
Requires-Dist: loguru (>=0.7.3,<0.8.0)
